{
  "type": "examplemod:add_item",
  "conditions": [
    {
      "condition": "minecraft:any_of",
      "terms": [
        {
          "condition": "forge:loot_table_id",
          "loot_table_id": "minecraft:entities/zombie"
        },
        {
          "condition": "forge:loot_table_id",
          "loot_table_id": "minecraft:entities/skeleton"
        },
        {
          "condition": "forge:loot_table_id",
          "loot_table_id": "minecraft:entities/spider"
        },
        {
          "condition": "forge:loot_table_id",
          "loot_table_id": "examplemod:entities/en_zombie_l1"
        }
      ]
    },
    {
      "chance": 1.0,
      "condition": "minecraft:random_chance"
    }
  ],
  "item": "examplemod:essence_t1"
}